chouette/__init__.py
chouette/_configuration.py
chouette/_scheduler.py
chouette/_singleton_actor.py
chouette/metrics/__init__.py
chouette/metrics/_aggregator.py
chouette/metrics/_collector.py
chouette/metrics/_metrics.py
chouette/metrics/_sender.py
chouette/metrics/plugins/__init__.py
chouette/metrics/plugins/_collector_plugin.py
chouette/metrics/plugins/_docker_collector.py
chouette/metrics/plugins/_dramatiq_collector.py
chouette/metrics/plugins/_host_collector.py
chouette/metrics/plugins/_k8s_collector.py
chouette/metrics/plugins/_tegrastats_collector.py
chouette/metrics/plugins/messages.py
chouette/metrics/wrappers/__init__.py
chouette/metrics/wrappers/_datadog_wrapper.py
chouette/metrics/wrappers/_metrics_wrapper.py
chouette/metrics/wrappers/_simple_wrapper.py
chouette/storages/__init__.py
chouette/storages/_redis.py
chouette/storages/_redis_messages.py
chouette/storages/messages.py
chouette_iot/__init__.py
chouette_iot/__main__.py
chouette_iot/_configuration.py
chouette_iot/_scheduler.py
chouette_iot/_singleton_actor.py
chouette_iot/metrics/__init__.py
chouette_iot/metrics/_aggregator.py
chouette_iot/metrics/_collector.py
chouette_iot/metrics/_metrics.py
chouette_iot/metrics/_sender.py
chouette_iot/metrics/plugins/__init__.py
chouette_iot/metrics/plugins/_collector_plugin.py
chouette_iot/metrics/plugins/_docker_collector.py
chouette_iot/metrics/plugins/_dramatiq_collector.py
chouette_iot/metrics/plugins/_host_collector.py
chouette_iot/metrics/plugins/_k8s_collector.py
chouette_iot/metrics/plugins/_tegrastats_collector.py
chouette_iot/metrics/plugins/messages.py
chouette_iot/metrics/wrappers/__init__.py
chouette_iot/metrics/wrappers/_datadog_wrapper.py
chouette_iot/metrics/wrappers/_metrics_wrapper.py
chouette_iot/metrics/wrappers/_simple_wrapper.py
chouette_iot/storages/__init__.py
chouette_iot/storages/_redis.py
chouette_iot/storages/_redis_messages.py
chouette_iot/storages/messages.py
chouette_iot-0.0.2.dist-info/LICENSE
chouette_iot-0.0.2.dist-info/METADATA
chouette_iot-0.0.2.dist-info/WHEEL
chouette_iot-0.0.2.dist-info/top_level.txt
chouette_iot-0.0.2.dist-info/RECORD
