Metadata-Version: 2.1
Name: chouette-iot
Version: 0.0.2
Summary: Monitoring and metrics collecting Datadog integration for IoT devices
Home-page: https://github.com/akatashev/chouette-iot
Author: Artem Katashev
Author-email: aharr@rowanleaf.net
License: Apache License, Version 2.0
Platform: UNKNOWN
Classifier: Intended Audience :: Developers
Classifier: License :: OSI Approved :: Apache Software License
Classifier: Operating System :: OS Independent
Classifier: Programming Language :: Python :: 3
Classifier: Topic :: System :: Monitoring
Requires-Python: >=3.6
Requires-Dist: redis
Requires-Dist: pykka
Requires-Dist: requests
Requires-Dist: requests-unixsocket
Requires-Dist: python-json-logger
Requires-Dist: psutil
Requires-Dist: pydantic
Requires-Dist: chouette-iot-client
